datatig/__init__.py
datatig/__main__.py
datatig/cli.py
datatig/exceptions.py
datatig/jsondeepreaderwriter.py
datatig/jsonschemabuilder.py
datatig/process.py
datatig/repository_access.py
datatig/sqlite.py
datatig/sqliteversioned.py
datatig/assets/__init__.py
datatig/assets/all/__init__.py
datatig/assets/all/logo.png
datatig/assets/all/main.css
datatig/assets/all/fontawesome-free-6-7-2-web/LICENSE.txt
datatig/assets/all/fontawesome-free-6-7-2-web/__init__.py
datatig/assets/all/fontawesome-free-6-7-2-web/css/__init__.py
datatig/assets/all/fontawesome-free-6-7-2-web/css/brands.min.css
datatig/assets/all/fontawesome-free-6-7-2-web/css/fontawesome.min.css
datatig/assets/all/fontawesome-free-6-7-2-web/css/solid.min.css
datatig/assets/all/fontawesome-free-6-7-2-web/webfonts/__init__.py
datatig/assets/all/fontawesome-free-6-7-2-web/webfonts/fa-brands-400.ttf
datatig/assets/all/fontawesome-free-6-7-2-web/webfonts/fa-brands-400.woff2
datatig/assets/all/fontawesome-free-6-7-2-web/webfonts/fa-solid-900.ttf
datatig/assets/all/fontawesome-free-6-7-2-web/webfonts/fa-solid-900.woff2
datatig/assets/localserver/__init__.py
datatig/assets/localserver/web-edit-or-new.js
datatig/assets/static/__init__.py
datatig/assets/static/web-edit-or-new.js
datatig/assets/staticversioned/__init__.py
datatig/localserver/__init__.py
datatig/localserver/app.py
datatig/localserver/datastore.py
datatig/localserver/run.py
datatig/localserver/settings.py
datatig/localserver/view_base.py
datatig/localserver/view_index.py
datatig/localserver/view_type_index.py
datatig/localserver/view_type_record_editweb.py
datatig/localserver/view_type_record_index.py
datatig/models/__init__.py
datatig/models/calendar.py
datatig/models/calendar_data.py
datatig/models/calendar_event.py
datatig/models/error.py
datatig/models/field.py
datatig/models/field_boolean.py
datatig/models/field_date.py
datatig/models/field_datetime.py
datatig/models/field_integer.py
datatig/models/field_list_dictionaries.py
datatig-0.8.0.dist-info/licenses/LICENSE
datatig-0.8.0.dist-info/METADATA
datatig-0.8.0.dist-info/WHEEL
datatig-0.8.0.dist-info/top_level.txt
datatig-0.8.0.dist-info/RECORD
